{
    "model_type": "XGBoostClassifier",
    "objective": "binary:logistic",
    "eval_metric": "logloss",
    "random_state": 42,
    "scale_pos_weight": 0.14054888915290484,
    "hyperparameter_bounds": {
        "max_depth": [
            3,
            6
        ],
        "learning_rate": [
            0.03,
            0.1
        ],
        "n_estimators": [
            300,
            800
        ],
        "subsample": [
            0.7,
            1.0
        ],
        "colsample_bytree": [
            0.7,
            1.0
        ]
    },
    "metric_priority": [
        "NPV",
        "Sensitivity",
        "AUROC"
    ],
    "feature_count": 37,
    "feature_names_path": "Processed/ESBL_Stage2_feature_names.json",
    "label_definition": "Phenotypic (CTX/CAZ/CRO) - FINAL"
}